sae_probes/__init__.py
sae_probes/constants.py
sae_probes/data/OOD data/5_hist_fig_ismale_OOD.csv.zst
sae_probes/data/OOD data/66_living-room_OOD.csv.zst
sae_probes/data/OOD data/66_living-room_translations.csv.zst
sae_probes/data/OOD data/67_social-security_OOD.csv.zst
sae_probes/data/OOD data/6_hist_fig_isamerican_OOD.csv.zst
sae_probes/data/OOD data/73_control-group_OOD.csv.zst
sae_probes/data/OOD data/7_hist_fig_ispolitician_OOD.csv.zst
sae_probes/data/OOD data/87_glue_cola_OOD.csv.zst
sae_probes/data/OOD data/90_glue_qnli_OOD.csv.zst
sae_probes/data/cleaned_data/100_news_fake.csv.zst
sae_probes/data/cleaned_data/101_disease_class.csv.zst
sae_probes/data/cleaned_data/102_twt_emotion.csv.zst
sae_probes/data/cleaned_data/103_it_tick.csv.zst
sae_probes/data/cleaned_data/105_click_bait.csv.zst
sae_probes/data/cleaned_data/106_hate_hate.csv.zst
sae_probes/data/cleaned_data/107_hate_offensive.csv.zst
sae_probes/data/cleaned_data/108_athlete_sport.csv.zst
sae_probes/data/cleaned_data/109_ball_ws.csv.zst
sae_probes/data/cleaned_data/10_nyc_borough.csv.zst
sae_probes/data/cleaned_data/110_aimade_humangpt3.csv.zst
sae_probes/data/cleaned_data/111_yelp_data.csv.zst
sae_probes/data/cleaned_data/112_amzn_rev.csv.zst
sae_probes/data/cleaned_data/113_movie_sent.csv.zst
sae_probes/data/cleaned_data/114_nyc_borough_Manhattan.csv.zst
sae_probes/data/cleaned_data/115_nyc_borough_Brooklyn.csv.zst
sae_probes/data/cleaned_data/116_nyc_borough_Bronx.csv.zst
sae_probes/data/cleaned_data/117_us_state_FL.csv.zst
sae_probes/data/cleaned_data/118_us_state_CA.csv.zst
sae_probes/data/cleaned_data/119_us_state_TX.csv.zst
sae_probes/data/cleaned_data/11_us_lat.csv.zst
sae_probes/data/cleaned_data/120_us_timezone_Chicago.csv.zst
sae_probes/data/cleaned_data/121_us_timezone_New_York.csv.zst
sae_probes/data/cleaned_data/122_us_timezone_Los_Angeles.csv.zst
sae_probes/data/cleaned_data/123_world_country_United_Kingdom.csv.zst
sae_probes/data/cleaned_data/124_world_country_United_States.csv.zst
sae_probes-0.2.0.dist-info/LICENSE
sae_probes-0.2.0.dist-info/METADATA
sae_probes-0.2.0.dist-info/WHEEL
sae_probes-0.2.0.dist-info/RECORD
