Metadata-Version: 2.3
Name: sae-probes
Version: 0.2.0
Summary: Sparse probing benchmark for Sparse Autoencoders derived from the paper "Are Sparse Autoencoders Useful? A Case Study in Sparse Probing"
License: MIT
Keywords: deep-learning,sparse-autoencoders,mechanistic-interpretability,PyTorch
Author: Subhash Kantamneni
Requires-Python: >=3.10,<4.0
Classifier: License :: OSI Approved :: MIT License
Classifier: Programming Language :: Python :: 3
Classifier: Programming Language :: Python :: 3.10
Classifier: Programming Language :: Python :: 3.11
Classifier: Programming Language :: Python :: 3.12
Classifier: Programming Language :: Python :: 3.13
Classifier: Topic :: Scientific/Engineering :: Artificial Intelligence
Requires-Dist: hf-transfer (>=0.1.9,<0.2.0)
Requires-Dist: pandas (>=2.2.3,<3.0.0)
Requires-Dist: sae-lens (>=5.0.0,<7.0.0)
Requires-Dist: scikit-learn (>=1.6.1,<2.0.0)
Requires-Dist: transformer-lens (>=2.15.4,<3.0.0)
Requires-Dist: xgboost (>=3.0.2,<4.0.0)
Requires-Dist: zstandard (>=0.19.0)
Project-URL: Homepage, https://github.com/sae-probes/sae-probes
Project-URL: Repository, https://github.com/sae-probes/sae-probes
